mediacatch_s2t/__init__.py
mediacatch_s2t/__main__.py
mediacatch_s2t/helper.py
mediacatch_s2t/uploader.py
mediacatch_s2t-2.0.1.dist-info/LICENSE
mediacatch_s2t-2.0.1.dist-info/METADATA
mediacatch_s2t-2.0.1.dist-info/WHEEL
mediacatch_s2t-2.0.1.dist-info/entry_points.txt
mediacatch_s2t-2.0.1.dist-info/top_level.txt
mediacatch_s2t-2.0.1.dist-info/RECORD
