Metadata-Version: 2.1
Name: mediacatch-s2t
Version: 2.0.1
Summary: Upload a media file and get the transcription link.
Author-email: MediaCatch <support@mediacatch.io>
License: Apache License
Project-URL: Homepage, https://github.com/mediacatch/mediacatch-s2t
Keywords: mediacatch,speech to text,uploader,nlp
Classifier: License :: OSI Approved :: MIT License
Classifier: Programming Language :: Python
Classifier: Programming Language :: Python :: 3
Requires-Python: >=3.9
License-File: LICENSE
Requires-Dist: importlib-metadata
Requires-Dist: requests
Requires-Dist: rich
Requires-Dist: langcodes
Provides-Extra: dev
Requires-Dist: black ; extra == 'dev'
Requires-Dist: bumpver ; extra == 'dev'
Requires-Dist: isort ; extra == 'dev'
Requires-Dist: pip-tools ; extra == 'dev'
Requires-Dist: pytest ; extra == 'dev'
Requires-Dist: responses ; extra == 'dev'
